rettxid/__init__.py
rettxid/_alphabet.py
rettxid/_format.py
rettxid/_generator.py
rettxid/_normalizer.py
rettxid/_validator.py
rettxid/py.typed
rettxid-1.0.0.dist-info/METADATA
rettxid-1.0.0.dist-info/WHEEL
rettxid-1.0.0.dist-info/licenses/LICENSE
rettxid-1.0.0.dist-info/RECORD
