Metadata-Version: 2.4
Name: rettxid
Version: 1.0.0
Summary: Generate, validate, and normalize rettX IDs for the Rett Syndrome Europe ecosystem
Project-URL: Homepage, https://github.com/rett-europe/rettxid
Project-URL: Documentation, https://github.com/rett-europe/rettxid#readme
Project-URL: Repository, https://github.com/rett-europe/rettxid
Author-email: Pedro Rocha <procha@rettsyndrome.eu>
License-Expression: MIT
License-File: LICENSE
Keywords: identifier,patient-id,pseudonymous,rettx
Classifier: Development Status :: 4 - Beta
Classifier: Intended Audience :: Developers
Classifier: License :: OSI Approved :: MIT License
Classifier: Operating System :: OS Independent
Classifier: Programming Language :: Python :: 3
Classifier: Programming Language :: Python :: 3.11
Classifier: Programming Language :: Python :: 3.12
Classifier: Programming Language :: Python :: 3.13
Classifier: Typing :: Typed
Requires-Python: >=3.11
Provides-Extra: dev
Requires-Dist: hypothesis>=6.0; extra == 'dev'
Requires-Dist: mypy>=1.0; extra == 'dev'
Requires-Dist: pytest-cov>=4.0; extra == 'dev'
Requires-Dist: pytest>=8.0; extra == 'dev'
Requires-Dist: ruff>=0.1; extra == 'dev'
